cloudformation_docs/__init__.py
cloudformation_docs/cli.py
cloudformation_docs/core.py
cloudformation_docs/sdk.py
cloudformation_docs-0.3.2.dist-info/METADATA
cloudformation_docs-0.3.2.dist-info/WHEEL
cloudformation_docs-0.3.2.dist-info/entry_points.txt
cloudformation_docs-0.3.2.dist-info/top_level.txt
cloudformation_docs-0.3.2.dist-info/RECORD
