Metadata-Version: 2.1
Name: cloudformation-docs
Version: 0.3.2
Summary: Generate docs from cloudformation templates
Home-page: https://github.com/eamonnfaherty/cloudformation-doc-generator
Author: Eamonn Faherty
Author-email: packages@designandsolve.co.uk
License: UNKNOWN
Platform: UNKNOWN
Classifier: Programming Language :: Python :: 3
Classifier: License :: OSI Approved :: MIT License
Classifier: Operating System :: OS Independent
Requires-Dist: click (==7.0)
Requires-Dist: Jinja2 (>=2.10.1)
Requires-Dist: cfn-flip (==1.2.0)
